s3redirect
