Metadata-Version: 1.0
Name: s3redirect
Version: 0.1.1
Summary: Synchronize web site redirects with an Amazon S3 bucket
Home-page: http://github.com/nathan11g/s3redirect/
Author: Nathan Grigg
Author-email: nathan@nathanamy.org
License: BSD
Keywords: Amazon,S3,static site,redirect
Platform: UNKNOWN
Classifier: Programming Language :: Python :: 2
Classifier: Programming Language :: Python :: 2.7
Classifier: License :: OSI Approved :: BSD License
Classifier: Operating System :: OS Independent
Classifier: Development Status :: 4 - Beta
Classifier: Intended Audience :: Developers
Classifier: Topic :: Internet
Classifier: Topic :: Utilities
Classifier: Environment :: Console
